navia/__init__.py
navia-0.0.1.dist-info/licenses/LICENSE
navia-0.0.1.dist-info/METADATA
navia-0.0.1.dist-info/WHEEL
navia-0.0.1.dist-info/top_level.txt
navia-0.0.1.dist-info/RECORD
