Metadata-Version: 2.4
Name: navia
Version: 0.0.1
Summary: Python navigation package
Author: Tershire
Requires-Python: >=3.13
License-File: LICENSE
Dynamic: license-file
